ubuntu_watch_packages/20201210-kernel-linux-only.yaml
ubuntu_watch_packages/20201210-kernel.yaml
ubuntu_watch_packages/CVE-2020-14386-kernel-only-config-all.yaml
ubuntu_watch_packages/CVE-2020-14386-kernel-only-config.yaml
ubuntu_watch_packages/CVE-2020-16119-CVE-2020-16120-kernel-only-config-all.yaml
ubuntu_watch_packages/__init__.py
ubuntu_watch_packages/bdmurray.config.yaml
ubuntu_watch_packages/dist-config.yaml
ubuntu_watch_packages/kernel-only-config.yaml
ubuntu_watch_packages/sample-kernel-only-config.yaml
ubuntu_watch_packages/simple-config.yaml
ubuntu_watch_packages/ubuntu_watch_packages.py
ubuntu_watch_packages/templates/package-stats.html
ubuntu_watch_packages-0.4.7.dist-info/METADATA
ubuntu_watch_packages-0.4.7.dist-info/WHEEL
ubuntu_watch_packages-0.4.7.dist-info/entry_points.txt
ubuntu_watch_packages-0.4.7.dist-info/top_level.txt
ubuntu_watch_packages-0.4.7.dist-info/RECORD
