Metadata-Version: 2.1
Name: ubuntu-watch-packages
Version: 0.4.7
Summary: Helpful utility to watch specified packages, using rmadison, in the ubuntu archive for transition between archive pockets
Home-page: 
Author: philroche
Author-email: phil.roche@canonical.com
Requires-Dist: babel
Requires-Dist: click
Requires-Dist: jinja2
Requires-Dist: python-debian
Requires-Dist: pyyaml
Requires-Dist: readchar
Requires-Dist: ubuntu-package-status (>=0.0.4)
